cloudwright_airtable/__init__.py
cloudwright_airtable-0.0.0.post1.dist-info/METADATA
cloudwright_airtable-0.0.0.post1.dist-info/WHEEL
cloudwright_airtable-0.0.0.post1.dist-info/top_level.txt
cloudwright_airtable-0.0.0.post1.dist-info/RECORD
