Metadata-Version: 2.1
Name: cloudwright-airtable
Version: 0.0.0.post1
Summary: cloudwright_airtable
Home-page: https://cloudwright.io
Author: cloudwright
Author-email: founders@cloudwright.io
License: UNKNOWN
Platform: UNKNOWN
Classifier: Programming Language :: Python :: 3
Classifier: Operating System :: OS Independent
